predeployed_generator/__init__.py
predeployed_generator/contract_generator.py
predeployed_generator/py.typed
predeployed_generator/tools.py
predeployed_generator/upgradeable_contract_generator.py
predeployed_generator/openzeppelin/__init__.py
predeployed_generator/openzeppelin/access_control_enumerable_generator.py
predeployed_generator/openzeppelin/openzeppelin_contract_generator.py
predeployed_generator/openzeppelin/proxy_admin_generator.py
predeployed_generator/openzeppelin/transparent_upgradeable_proxy_generator.py
predeployed_generator/openzeppelin/artifacts/.keep
predeployed_generator/openzeppelin/artifacts/ProxyAdmin.json
predeployed_generator/openzeppelin/artifacts/ProxyAdmin.meta.json
predeployed_generator/openzeppelin/artifacts/TransparentUpgradeableProxy.json
predeployed_generator/openzeppelin/artifacts/TransparentUpgradeableProxy.meta.json
predeployed_generator-1.2.0.dist-info/LICENSE
predeployed_generator-1.2.0.dist-info/METADATA
predeployed_generator-1.2.0.dist-info/WHEEL
predeployed_generator-1.2.0.dist-info/top_level.txt
predeployed_generator-1.2.0.dist-info/RECORD
