Metadata-Version: 2.1
Name: predeployed-generator
Version: 1.2.0
Summary: A tool for generating memory layout of smart contracts written in solidity
Home-page: https://github.com/skalenetwork/predeployed-generator
Author: Dmytro Stebaiev
Author-email: dmytro@skalelabs.com
Classifier: Programming Language :: Python :: 3
Classifier: License :: OSI Approved :: GNU Affero General Public License v3
Classifier: Operating System :: OS Independent
Requires-Python: >=3.7
License-File: LICENSE
Requires-Dist: web3 (>=6.0.0)
